interest_theory/__init__.py
interest_theory/__pycache__/__init__.cpython-312.pyc
interest_theory/bonds/__init__.py
interest_theory/bonds/bond.py
interest_theory/bonds/__pycache__/__init__.cpython-312.pyc
interest_theory/bonds/__pycache__/bond.cpython-312.pyc
interest_theory/interest_rates/__init__.py
interest_theory/interest_rates/interest_rate.py
interest_theory/interest_rates/__pycache__/__init__.cpython-312.pyc
interest_theory/interest_rates/__pycache__/interest_rate.cpython-312.pyc
interest_theory-0.0.5.dist-info/LICENSE
interest_theory-0.0.5.dist-info/METADATA
interest_theory-0.0.5.dist-info/WHEEL
interest_theory-0.0.5.dist-info/top_level.txt
interest_theory-0.0.5.dist-info/RECORD
