Metadata-Version: 2.2
Name: interest-theory
Version: 0.0.5
Summary: Useful tools for interest theory
Home-page: https://github.com/alejandro77palacios/interest_theory
Author: Alejandro Prieto Palacios
Author-email: "Alejandro" <alex_palacios77@icloud.com>
License: MIT
Classifier: License :: OSI Approved :: MIT License
License-File: LICENSE
